<drawing><figures><rel id="0"><children><diamond id="1" x="485" y="540" w="80" h="40"><a><fillColor><color rgba="#ffddddff"/></fillColor></a></diamond><t id="2" x="505.0048828125" y="553.015625"><a><text><string>realiza</string></text></a></t></children></rel><atr id="3" nullable="false" attributeType="VARCHAR2(128)"><children><e id="4" x="619" y="638" w="80" h="20"><a><fillColor><color rgba="#ffffebeb"/></fillColor></a></e><t id="5" x="628.8681640625" y="641.015625"><a><text><string>data_hora</string></text></a></t></children></atr><atr id="6" nullable="false" attributeType="VARCHAR2(128)"><children><e id="7" x="372" y="731" w="80" h="20"><a><fillColor><color rgba="#ffffebeb"/></fillColor></a></e><t id="8" x="394.990234375" y="734.015625"><a><text><string>nome</string></text></a></t></children></atr><atr id="9" nullable="false" attributeType="VARCHAR2(128)"><children><e id="a" x="515" y="730" w="80" h="20"><a><fillColor><color rgba="#ffffebeb"/></fillColor></a></e><t id="b" x="530.5986328125" y="733.015625"><a><text><string>dura&#xe7;&#xe3;o</string></text></a></t></children></atr><atrchave id="c" nullable="false" attributeType="NUMBER"><children><e id="d" x="339" y="638" w="80" h="20"><a><fillColor><color rgba="#ffffebeb"/></fillColor></a></e><t id="e" x="372.6484375" y="641.015625"><a><fontUnderlined><boolean>true</boolean></fontUnderlined><fontBold><boolean>true</boolean></fontBold><text><string>id</string></text></a></t></children></atrchave><ent id="f"><children><r id="10" x="462" y="207" w="109" h="57"><a><fillColor><color rgba="#ffebffe8"/></fillColor></a></r><t id="11" x="498.6552734375" y="228.515625"><a><text><string>Atleta</string></text></a></t></children></ent><ent id="12"><children><r id="13" x="445" y="428" w="153.447265625" h="65"><a><fillColor><color rgba="#ffebffe8"/></fillColor></a></r><t id="14" x="487.0712890625" y="453.515625"><a><text><string>Modalidade</string></text></a></t></children></ent><atrchave id="15" nullable="false" attributeType="NUMBER"><children><e id="16" x="285" y="249" w="80" h="20"><a><fillColor><color rgba="#ffffebeb"/></fillColor></a></e><t id="17" x="318.47265625" y="252.015625"><a><fontUnderlined><boolean>true</boolean></fontUnderlined><fontBold><boolean>true</boolean></fontBold><text><string>Id</string></text></a></t></children></atrchave><atr id="18" nullable="false" attributeType="VARCHAR2(128)"><children><e id="19" x="315" y="103" w="85" h="25"><a><fillColor><color rgba="#ffffebeb"/></fillColor></a></e><t id="1a" x="340.490234375" y="108.515625"><a><text><string>nome</string></text></a></t></children></atr><atr id="1b" nullable="false" attributeType="VARCHAR2(128)"><children><e id="1c" x="537" y="109" w="89" h="22"><a><fillColor><color rgba="#ffffebeb"/></fillColor></a></e><t id="1d" x="558.35546875" y="113.015625"><a><text><string>morada</string></text></a></t></children></atr><atr id="1e" nullable="false" attributeType="VARCHAR2(128)"><children><e id="1f" x="596" y="165" w="90" h="24"><a><fillColor><color rgba="#ffffebeb"/></fillColor></a></e><t id="20" x="627.541015625" y="170.015625"><a><text><string>DOB</string></text></a></t></children></atr><lcaf id="21"><points><p colinear="true" x="365" y="254.09138381201043" c1x="0" c1y="0" c2x="0" c2y="0"/><p colinear="true" x="462" y="242.18798955613576" c1x="0" c1y="0" c2x="0" c2y="0"/></points><startConnector><rConnector id="22"><Owner><atrchave ref="15"/></Owner></rConnector></startConnector><endConnector><rConnector id="23"><Owner><ent ref="f"/></Owner></rConnector></endConnector></lcaf><lcaf id="24"><points><p colinear="true" x="374.0625" y="128" c1x="0" c1y="0" c2x="0" c2y="0"/><p colinear="true" x="478.7375" y="207" c1x="0" c1y="0" c2x="0" c2y="0"/></points><startConnector><rConnector id="25"><Owner><atr ref="18"/></Owner></rConnector></startConnector><endConnector><rConnector id="26"><Owner><ent ref="f"/></Owner></rConnector></endConnector></lcaf><lcaf id="27"><points><p colinear="true" x="575.3095238095239" y="131" c1x="0" c1y="0" c2x="0" c2y="0"/><p colinear="true" x="532.538961038961" y="207" c1x="0" c1y="0" c2x="0" c2y="0"/></points><startConnector><rConnector id="28"><Owner><atr ref="1b"/></Owner></rConnector></startConnector><endConnector><rConnector id="29"><Owner><ent ref="f"/></Owner></rConnector></endConnector></lcaf><lcaf id="2a"><points><p colinear="true" x="615.4615384615385" y="189" c1x="0" c1y="0" c2x="0" c2y="0"/><p colinear="true" x="571" y="209.89156626506025" c1x="0" c1y="0" c2x="0" c2y="0"/></points><startConnector><rConnector id="2b"><Owner><atr ref="1e"/></Owner></rConnector></startConnector><endConnector><rConnector id="2c"><Owner><ent ref="f"/></Owner></rConnector></endConnector></lcaf><atr id="2d" nullable="false" attributeType="VARCHAR2(128)"><children><e id="2e" x="617" y="415" w="94" h="29"><a><fillColor><color rgba="#ffffebeb"/></fillColor></a></e><t id="2f" x="646.990234375" y="422.515625"><a><text><string>nome</string></text></a></t></children></atr><atrchave id="30" nullable="false" attributeType="NUMBER"><children><e id="31" x="643" y="474" w="87" h="24"><a><fillColor><color rgba="#ffffebeb"/></fillColor></a></e><t id="32" x="679.97265625" y="479.015625"><a><fontUnderlined><boolean>true</boolean></fontUnderlined><fontBold><boolean>true</boolean></fontBold><text><string>Id</string></text></a></t></children></atrchave><lcaf id="33"><points><p colinear="true" x="598.447265625" y="443.78300993197934" c1x="0" c1y="0" c2x="0" c2y="0"/><p colinear="true" x="617" y="439.7406325716757" c1x="0" c1y="0" c2x="0" c2y="0"/></points><startConnector><rConnector id="34"><Owner><ent ref="12"/></Owner></rConnector></startConnector><endConnector><rConnector id="35"><Owner><atr ref="2d"/></Owner></rConnector></endConnector></lcaf><lcaf id="36"><points><p colinear="true" x="598.447265625" y="472.3733812992278" c1x="0" c1y="0" c2x="0" c2y="0"/><p colinear="true" x="643" y="479.268148710077" c1x="0" c1y="0" c2x="0" c2y="0"/></points><startConnector><rConnector id="37"><Owner><ent ref="12"/></Owner></rConnector></startConnector><endConnector><rConnector id="38"><Owner><atrchave ref="30"/></Owner></rConnector></endConnector></lcaf><ent id="39"><children><r id="3a" x="962" y="217" w="80" h="40"><a><fillColor><color rgba="#ffebffe8"/></fillColor></a></r><t id="3b" x="965.5107421875" y="230.015625"><a><text><string>TesteCl&#xed;nico</string></text></a></t></children></ent><rel id="3c"><children><diamond id="3d" x="774" y="215" w="80" h="40"><a><fillColor><color rgba="#ffddddff"/></fillColor></a></diamond><t id="3e" x="794.0048828125" y="228.015625"><a><text><string>realiza</string></text></a></t></children></rel><llabelMuitos id="3f"><points><p colinear="true" x="774" y="235.0672268907563" c1x="0" c1y="0" c2x="0" c2y="0"/><p colinear="true" x="571" y="235.40840336134454" c1x="0" c1y="0" c2x="0" c2y="0"/></points><startConnector><rConnector id="40"><Owner><rel ref="3c"/></Owner></rConnector></startConnector><endConnector><rConnector id="41"><Owner><ent ref="f"/></Owner></rConnector></endConnector><a><text><string>N</string></text></a></llabelMuitos><llabelMuitos id="42"><points><p colinear="true" x="854" y="235.4255319148936" c1x="0" c1y="0" c2x="0" c2y="0"/><p colinear="true" x="962" y="236.5744680851064" c1x="0" c1y="0" c2x="0" c2y="0"/></points><startConnector><rConnector id="43"><Owner><rel ref="3c"/></Owner></rConnector></startConnector><endConnector><rConnector id="44"><Owner><ent ref="39"/></Owner></rConnector></endConnector><a><text><string>M</string></text></a></llabelMuitos><atr id="45" nullable="false" attributeType="VARCHAR2(128)"><children><e id="46" x="956" y="339" w="80" h="20"><a><fillColor><color rgba="#ffffebeb"/></fillColor></a></e><t id="47" x="979.0634765625" y="342.015625"><a><text><string>preco</string></text></a></t></children></atr><atr id="48" nullable="false" attributeType="VARCHAR2(128)"><children><e id="49" x="855" y="340" w="80" h="20"><a><fillColor><color rgba="#ffffebeb"/></fillColor></a></e><t id="4a" x="870.5986328125" y="343.015625"><a><text><string>dura&#xe7;&#xe3;o</string></text></a></t></children></atr><atr id="4b" nullable="false" attributeType="VARCHAR2(128)"><children><e id="4c" x="1054" y="356" w="80" h="20"><a><fillColor><color rgba="#ffffebeb"/></fillColor></a></e><t id="4d" x="1063.8681640625" y="359.015625"><a><text><string>data_hora</string></text></a></t></children></atr><atrchave id="4e" nullable="false" attributeType="NUMBER"><children><e id="4f" x="1017" y="159" w="80" h="20"><a><fillColor><color rgba="#ffffebeb"/></fillColor></a></e><t id="50" x="1050.6484375" y="162.015625"><a><fontUnderlined><boolean>true</boolean></fontUnderlined><fontBold><boolean>true</boolean></fontBold><text><string>id</string></text></a></t></children></atrchave><atr id="51" nullable="false" attributeType="VARCHAR2(128)"><children><e id="52" x="1101" y="261" w="80" h="20"><a><fillColor><color rgba="#ffffebeb"/></fillColor></a></e><t id="53" x="1123.990234375" y="264.015625"><a><text><string>nome</string></text></a></t></children></atr><atr id="54" nullable="false" attributeType="VARCHAR2(128)"><children><e id="55" x="1110" y="309" w="80" h="20"><a><fillColor><color rgba="#ffffebeb"/></fillColor></a></e><t id="56" x="1122.525390625" y="312.015625"><a><text><string>realizado</string></text></a></t></children></atr><lcaf id="57"><points><p colinear="true" x="1048.9117647058824" y="179" c1x="0" c1y="0" c2x="0" c2y="0"/><p colinear="true" x="1018.1764705882352" y="217" c1x="0" c1y="0" c2x="0" c2y="0"/></points><startConnector><rConnector id="58"><Owner><atrchave ref="4e"/></Owner></rConnector></startConnector><endConnector><rConnector id="59"><Owner><ent ref="39"/></Owner></rConnector></endConnector></lcaf><lcaf id="5a"><points><p colinear="true" x="1101" y="261.2158273381295" c1x="0" c1y="0" c2x="0" c2y="0"/><p colinear="true" x="1042" y="246.7841726618705" c1x="0" c1y="0" c2x="0" c2y="0"/></points><startConnector><rConnector id="5b"><Owner><atr ref="51"/></Owner></rConnector></startConnector><endConnector><rConnector id="5c"><Owner><ent ref="39"/></Owner></rConnector></endConnector></lcaf><lcaf id="5d"><points><p colinear="true" x="1131.9512195121952" y="309" c1x="0" c1y="0" c2x="0" c2y="0"/><p colinear="true" x="1038.0975609756097" y="257" c1x="0" c1y="0" c2x="0" c2y="0"/></points><startConnector><rConnector id="5e"><Owner><atr ref="54"/></Owner></rConnector></startConnector><endConnector><rConnector id="5f"><Owner><ent ref="39"/></Owner></rConnector></endConnector></lcaf><lcaf id="60"><points><p colinear="true" x="1086.8682170542636" y="356" c1x="0" c1y="0" c2x="0" c2y="0"/><p colinear="true" x="1016.2635658914728" y="257" c1x="0" c1y="0" c2x="0" c2y="0"/></points><startConnector><rConnector id="61"><Owner><atr ref="4b"/></Owner></rConnector></startConnector><endConnector><rConnector id="62"><Owner><ent ref="39"/></Owner></rConnector></endConnector></lcaf><lcaf id="63"><points><p colinear="true" x="996.5357142857143" y="339" c1x="0" c1y="0" c2x="0" c2y="0"/><p colinear="true" x="1000.9285714285714" y="257" c1x="0" c1y="0" c2x="0" c2y="0"/></points><startConnector><rConnector id="64"><Owner><atr ref="45"/></Owner></rConnector></startConnector><endConnector><rConnector id="65"><Owner><ent ref="39"/></Owner></rConnector></endConnector></lcaf><lcaf id="66"><points><p colinear="true" x="904.4690265486726" y="340" c1x="0" c1y="0" c2x="0" c2y="0"/><p colinear="true" x="983.0619469026549" y="257" c1x="0" c1y="0" c2x="0" c2y="0"/></points><startConnector><rConnector id="67"><Owner><atr ref="48"/></Owner></rConnector></startConnector><endConnector><rConnector id="68"><Owner><ent ref="39"/></Owner></rConnector></endConnector></lcaf><atr id="69" nullable="false" attributeType="VARCHAR2(128)"><children><e id="6a" x="168" y="193" w="80" h="20"><a><fillColor><color rgba="#ffffebeb"/></fillColor></a></e><t id="6b" x="193.9609375" y="196.015625"><a><text><string>sexo</string></text></a></t></children></atr><lcaf id="6c"><points><p colinear="true" x="248" y="207.21393841166937" c1x="0" c1y="0" c2x="0" c2y="0"/><p colinear="true" x="462" y="229.7585089141005" c1x="0" c1y="0" c2x="0" c2y="0"/></points><startConnector><rConnector id="6d"><Owner><atr ref="69"/></Owner></rConnector></startConnector><endConnector><rConnector id="6e"><Owner><ent ref="f"/></Owner></rConnector></endConnector></lcaf><rel id="6f"><children><diamond id="70" x="480" y="320" w="80" h="40"><a><fillColor><color rgba="#ffddddff"/></fillColor></a></diamond><t id="71" x="502.3427734375" y="333.015625"><a><text><string>treina</string></text></a></t></children></rel><llabelMuitos id="72"><points><p colinear="true" x="519.3301435406698" y="320" c1x="0" c1y="0" c2x="0" c2y="0"/><p colinear="true" x="517.4545454545455" y="264" c1x="0" c1y="0" c2x="0" c2y="0"/></points><startConnector><rConnector id="73"><Owner><rel ref="6f"/></Owner></rConnector></startConnector><endConnector><rConnector id="74"><Owner><ent ref="f"/></Owner></rConnector></endConnector><a><text><string>N</string></text></a></llabelMuitos><llabelUm id="75"><points><p colinear="true" x="520.2860801348547" y="360" c1x="0" c1y="0" c2x="0" c2y="0"/><p colinear="true" x="521.258752593361" y="428" c1x="0" c1y="0" c2x="0" c2y="0"/></points><startConnector><rConnector id="76"><Owner><rel ref="6f"/></Owner></rConnector></startConnector><endConnector><rConnector id="77"><Owner><ent ref="12"/></Owner></rConnector></endConnector></llabelUm><atr id="78" nullable="false" attributeType="VARCHAR2(128)"><children><e id="79" x="287" y="163" w="80" h="20"><a><fillColor><color rgba="#ffffebeb"/></fillColor></a></e><t id="7a" x="312.703125" y="166.015625"><a><text><string>peso</string></text></a></t></children></atr><atr id="7b" nullable="false" attributeType="VARCHAR2(128)"><children><e id="7c" x="441" y="144" w="80" h="23"><a><fillColor><color rgba="#ffffebeb"/></fillColor></a></e><t id="7d" x="463.357421875" y="148.515625"><a><text><string>altura</string></text></a></t></children></atr><lcaf id="7e"><points><p colinear="true" x="462" y="217.52506596306068" c1x="63.03244837758112" c1y="64" c2x="63.03244837758112" c2y="64"/><p colinear="true" x="357.32" y="183" c1x="63.03244837758112" c1y="64" c2x="63.03244837758112" c2y="64"/></points><startConnector><rConnector id="7f"><Owner><ent ref="f"/></Owner></rConnector></startConnector><endConnector><rConnector id="80"><Owner><atr ref="78"/></Owner></rConnector></endConnector></lcaf><lcaf id="81"><points><p colinear="true" x="503.853125" y="207" c1x="0" c1y="0" c2x="0" c2y="0"/><p colinear="true" x="486.103125" y="167" c1x="0" c1y="0" c2x="0" c2y="0"/></points><startConnector><rConnector id="82"><Owner><ent ref="f"/></Owner></rConnector></startConnector><endConnector><rConnector id="83"><Owner><atr ref="7b"/></Owner></rConnector></endConnector></lcaf><rel id="84"><children><diamond id="85" x="1227" y="215" w="80" h="40"><a><fillColor><color rgba="#ffddddff"/></fillColor></a></diamond><t id="86" x="1239.525390625" y="228.015625"><a><text><string>realizado</string></text></a></t></children></rel><ent id="87"><children><r id="88" x="1406" y="216" w="80" h="40"><a><fillColor><color rgba="#ffebffe8"/></fillColor></a></r><t id="89" x="1411.728515625" y="229.015625"><a><text><string>Profissional</string></text></a></t></children></ent><llabelMuitos id="8a"><points><p colinear="true" x="1227" y="235.30188679245282" c1x="0" c1y="0" c2x="0" c2y="0"/><p colinear="true" x="1042" y="236.69811320754718" c1x="0" c1y="0" c2x="0" c2y="0"/></points><startConnector><rConnector id="8b"><Owner><rel ref="84"/></Owner></rConnector></startConnector><endConnector><rConnector id="8c"><Owner><ent ref="39"/></Owner></rConnector></endConnector><a><text><string>N</string></text></a></llabelMuitos><llabelMuitos id="8d"><points><p colinear="true" x="1307" y="235.22346368715085" c1x="0" c1y="0" c2x="0" c2y="0"/><p colinear="true" x="1406" y="235.77653631284917" c1x="0" c1y="0" c2x="0" c2y="0"/></points><startConnector><rConnector id="8e"><Owner><rel ref="84"/></Owner></rConnector></startConnector><endConnector><rConnector id="8f"><Owner><ent ref="87"/></Owner></rConnector></endConnector><a><text><string>M</string></text></a></llabelMuitos><atrchave id="90" nullable="false" attributeType="NUMBER"><children><e id="91" x="1407" y="151" w="80" h="20"><a><fillColor><color rgba="#ffffebeb"/></fillColor></a></e><t id="92" x="1440.6484375" y="154.015625"><a><fontUnderlined><boolean>true</boolean></fontUnderlined><fontBold><boolean>true</boolean></fontBold><text><string>id</string></text></a></t></children></atrchave><atr id="93" nullable="false" attributeType="VARCHAR2(128)"><children><e id="94" x="1536" y="190" w="80" h="20"><a><fillColor><color rgba="#ffffebeb"/></fillColor></a></e><t id="95" x="1558.990234375" y="193.015625"><a><text><string>nome</string></text></a></t></children></atr><lcaf id="96"><points><p colinear="true" x="1446.8666666666666" y="171" c1x="0" c1y="0" c2x="0" c2y="0"/><p colinear="true" x="1446.2666666666667" y="216" c1x="0" c1y="0" c2x="0" c2y="0"/></points><startConnector><rConnector id="97"><Owner><atrchave ref="90"/></Owner></rConnector></startConnector><endConnector><rConnector id="98"><Owner><ent ref="87"/></Owner></rConnector></endConnector></lcaf><lcaf id="99"><points><p colinear="true" x="1539.888888888889" y="210" c1x="0" c1y="0" c2x="0" c2y="0"/><p colinear="true" x="1486" y="224.92307692307693" c1x="0" c1y="0" c2x="0" c2y="0"/></points><startConnector><rConnector id="9a"><Owner><atr ref="93"/></Owner></rConnector></startConnector><endConnector><rConnector id="9b"><Owner><ent ref="87"/></Owner></rConnector></endConnector></lcaf><llabelUm id="9c"><points><p colinear="true" x="524.3414337311558" y="540" c1x="0" c1y="0" c2x="0" c2y="0"/><p colinear="true" x="522.7938029993719" y="493" c1x="0" c1y="0" c2x="0" c2y="0"/></points><startConnector><rConnector id="9d"><Owner><rel ref="0"/></Owner></rConnector></startConnector><endConnector><rConnector id="9e"><Owner><ent ref="12"/></Owner></rConnector></endConnector></llabelUm><entfraca id="9f"><children><r id="a0" x="475" y="634" w="101" h="57"><a><fillColor><color rgba="#ffebffe8"/></fillColor><strokeType><enum type="strokeType">DOUBLE</enum></strokeType><innerStrokeWidthFactor><double>3</double></innerStrokeWidthFactor></a></r><t id="a1" x="508.5166015625" y="655.515625"><a><text><string>Prova</string></text></a></t></children></entfraca><llabelMuitos id="a2"><points><p colinear="true" x="525.0975609756098" y="580" c1x="0" c1y="0" c2x="0" c2y="0"/><p colinear="true" x="525.3609756097561" y="634" c1x="0" c1y="0" c2x="0" c2y="0"/></points><startConnector><rConnector id="a3"><Owner><rel ref="0"/></Owner></rConnector></startConnector><endConnector><rConnector id="a4"><Owner><entfraca ref="9f"/></Owner></rConnector></endConnector><a><text><string>N</string></text></a></llabelMuitos><lcaf id="a5"><points><p colinear="true" x="475" y="657.5017064846417" c1x="0" c1y="0" c2x="0" c2y="0"/><p colinear="true" x="419" y="651.9590443686006" c1x="0" c1y="0" c2x="0" c2y="0"/></points><startConnector><rConnector id="a6"><Owner><entfraca ref="9f"/></Owner></rConnector></startConnector><endConnector><rConnector id="a7"><Owner><atrchave ref="c"/></Owner></rConnector></endConnector></lcaf><lcaf id="a8"><points><p colinear="true" x="536.3483870967742" y="691" c1x="0" c1y="0" c2x="0" c2y="0"/><p colinear="true" x="551.1935483870968" y="730" c1x="0" c1y="0" c2x="0" c2y="0"/></points><startConnector><rConnector id="a9"><Owner><entfraca ref="9f"/></Owner></rConnector></startConnector><endConnector><rConnector id="aa"><Owner><atr ref="9"/></Owner></rConnector></endConnector></lcaf><lcaf id="ab"><points><p colinear="true" x="484.2929936305733" y="691" c1x="0" c1y="0" c2x="0" c2y="0"/><p colinear="true" x="426.45859872611464" y="731" c1x="0" c1y="0" c2x="0" c2y="0"/></points><startConnector><rConnector id="ac"><Owner><entfraca ref="9f"/></Owner></rConnector></startConnector><endConnector><rConnector id="ad"><Owner><atr ref="6"/></Owner></rConnector></endConnector></lcaf><lcaf id="ae"><points><p colinear="true" x="619" y="652.3445692883895" c1x="0" c1y="0" c2x="0" c2y="0"/><p colinear="true" x="576" y="657.0149812734082" c1x="0" c1y="0" c2x="0" c2y="0"/></points><startConnector><rConnector id="af"><Owner><atr ref="3"/></Owner></rConnector></startConnector><endConnector><rConnector id="b0"><Owner><entfraca ref="9f"/></Owner></rConnector></endConnector></lcaf></figures></drawing>